{"_studyhub":true,"_syncMode":"delta","_version":55,"_exportedAt":"2026-06-13T01:09:53.336Z","_deviceId":"dev-mq8ihaj2nbchxg","_stats":{"contentDelta":8,"ratingCount":3},"classes":[{"id":"class8","name":"Class 8","icon":"🎓"}],"subjects":[{"id":"physics","classId":"class8","name":"Physics","icon":"⚛️","color":"physics"},{"id":"chemistry","classId":"class8","name":"Chemistry","icon":"🧪","color":"chemistry"},{"id":"biology","classId":"class8","name":"Biology","icon":"🧬","color":"biology"},{"id":"history","classId":"class8","name":"History","icon":"📜","color":"history"},{"id":"geography","classId":"class8","name":"Geography","icon":"🌏","color":"geography"},{"id":"civics","classId":"class8","name":"Civics","icon":"⚖️","color":"civics"}],"topics":[{"id":"ch1-matter","subjectId":"physics","classId":"class8","name":"Chapter 1: Matter","icon":"🔬"},{"id":"ch2-measurement","subjectId":"physics","classId":"class8","name":"Chapter 2: Physical Quantities & Measurement","icon":"📏"},{"id":"ch3-force","subjectId":"physics","classId":"class8","name":"Chapter 3: Force and Pressure","icon":"💪"},{"id":"ch4-energy","subjectId":"physics","classId":"class8","name":"Chapter 4: Energy","icon":"⚡"},{"id":"ch5-light","subjectId":"physics","classId":"class8","name":"Chapter 5: Light Energy","icon":"💡"},{"id":"ch6-heat","subjectId":"physics","classId":"class8","name":"Chapter 6: Heat Transfer","icon":"🌡️"},{"id":"ch7-sound","subjectId":"physics","classId":"class8","name":"Chapter 7: Sound","icon":"🔊"},{"id":"ch8-electricity","subjectId":"physics","classId":"class8","name":"Chapter 8: Electricity","icon":"🔌"},{"id":"bio-ch1","subjectId":"biology","classId":"class8","name":"Chapter 1: Transportation in Plants","icon":"🌿"},{"id":"bio-ch2","subjectId":"biology","classId":"class8","name":"Chapter 2: Reproduction in Plants","icon":"🌸"},{"id":"bio-ch3","subjectId":"biology","classId":"class8","name":"Chapter 3: Reproduction in Humans","icon":"👶"},{"id":"bio-ch4","subjectId":"biology","classId":"class8","name":"Chapter 4: Ecosystems","icon":"🌍"},{"id":"bio-ch5","subjectId":"biology","classId":"class8","name":"Chapter 5: Endocrine System & Adolescence","icon":"🧬"},{"id":"bio-ch6","subjectId":"biology","classId":"class8","name":"Chapter 6: The Circulatory System","icon":"❤️"},{"id":"bio-ch7","subjectId":"biology","classId":"class8","name":"Chapter 7: Nervous System","icon":"🧠"},{"id":"bio-ch8","subjectId":"biology","classId":"class8","name":"Chapter 8: Diseases and First Aid","icon":"🏥"},{"id":"bio-ch9","subjectId":"biology","classId":"class8","name":"Chapter 9: Food Production","icon":"🌾"},{"id":"chem-ch1","subjectId":"chemistry","classId":"class8","name":"Chapter 1: Matter","icon":"🧪"},{"id":"chem-ch2","subjectId":"chemistry","classId":"class8","name":"Chapter 2: Physical & Chemical Changes","icon":"🔥"},{"id":"chem-ch3","subjectId":"chemistry","classId":"class8","name":"Chapter 3: Elements, Compounds & Mixtures","icon":"⚗️"},{"id":"chem-ch4","subjectId":"chemistry","classId":"class8","name":"Chapter 4: Atomic Structure","icon":"⚛️"},{"id":"chem-ch5","subjectId":"chemistry","classId":"class8","name":"Chapter 5: Language of Chemistry","icon":"📝"},{"id":"chem-ch6","subjectId":"chemistry","classId":"class8","name":"Chapter 6: Chemical Reactions","icon":"💥"},{"id":"chem-ch7","subjectId":"chemistry","classId":"class8","name":"Chapter 7: Hydrogen","icon":"💨"},{"id":"chem-ch8","subjectId":"chemistry","classId":"class8","name":"Chapter 8: Water","icon":"💧"},{"id":"chem-ch9","subjectId":"chemistry","classId":"class8","name":"Chapter 9: Carbon & Its Compounds","icon":"💎"},{"id":"hist-ch1","subjectId":"history","classId":"class8","name":"Ch 1: A Period of Transition","icon":"🏰"},{"id":"hist-ch2","subjectId":"history","classId":"class8","name":"Ch 2: The Age of Revolutions","icon":"🇫🇷"},{"id":"hist-ch3","subjectId":"history","classId":"class8","name":"Ch 3: American Civil War","icon":"🇺🇸"},{"id":"hist-ch4","subjectId":"history","classId":"class8","name":"Ch 4: Decline of the Mughal Empire","icon":"👑"},{"id":"hist-ch6","subjectId":"history","classId":"class8","name":"Ch 6: British Conquest of Bengal","icon":"⚔️"},{"id":"hist-ch7","subjectId":"history","classId":"class8","name":"Ch 7: Expansion of British Power","icon":"🗺️"},{"id":"hist-ch8","subjectId":"history","classId":"class8","name":"Ch 8: Impact of British Rule","icon":"📉"},{"id":"hist-ch9","subjectId":"history","classId":"class8","name":"Ch 9: Great Uprising of 1857","icon":"🔥"},{"id":"hist-ch10","subjectId":"history","classId":"class8","name":"Ch 10: Reform Movements","icon":"✊"},{"id":"civ-ch1","subjectId":"civics","classId":"class8","name":"Civics 1: Organs of Government","icon":"🏛️"},{"id":"civ-ch2","subjectId":"civics","classId":"class8","name":"Civics 2: The United Nations","icon":"🌐"},{"id":"geo-ch1","subjectId":"geography","classId":"class8","name":"Ch 1: Topographical Maps","icon":"🗺️"},{"id":"geo-ch2","subjectId":"geography","classId":"class8","name":"Ch 2: Population","icon":"👥"},{"id":"geo-ch3","subjectId":"geography","classId":"class8","name":"Ch 3: Migration","icon":"✈️"},{"id":"geo-ch4","subjectId":"geography","classId":"class8","name":"Ch 4: Urbanization","icon":"🏙️"},{"id":"geo-ch5","subjectId":"geography","classId":"class8","name":"Ch 5: Disasters & Management","icon":"🌊"},{"id":"geo-ch6","subjectId":"geography","classId":"class8","name":"Ch 6: Asia — Physical & Climate","icon":"🌏"},{"id":"geo-ch7","subjectId":"geography","classId":"class8","name":"Ch 7: India — Physical & Climate","icon":"🇮🇳"},{"id":"geo-ch8","subjectId":"geography","classId":"class8","name":"Ch 8: Human Resources","icon":"🧑‍🎓"},{"id":"hist-ch5","subjectId":"history","classId":"class8","name":"Ch 5: English East India Company","icon":"🚢"},{"id":"hist-ch11","subjectId":"history","classId":"class8","name":"Ch 11: Rise of Indian Nationalism","icon":"🇮🇳"},{"id":"hist-ch12","subjectId":"history","classId":"class8","name":"Ch 12: National Movement 1885–1916","icon":"📜"},{"id":"hist-ch13","subjectId":"history","classId":"class8","name":"Ch 13: Gandhi Era 1917–1947","icon":"🕊️"},{"id":"ch9-modern","subjectId":"physics","classId":"class8","name":"Chapter 9: Modern Physics","icon":"⚡"},{"id":"ch10-olympiad","subjectId":"physics","classId":"class8","name":"Chapter 10: Olympiad Masterclass","icon":"🏆"}],"content":[{"id":"pqb-ch1-matter-11","topicId":"ch1-matter","type":"short_answer","subtopic":"Additional Questions","question":"1) Differentiate between solids, liquids and gases on the basis of kinetic theory.","answer":"<table border=\"1\" cellpadding=\"8\" cellspacing=\"0\" style=\"border-collapse: collapse; width: 100%; text-align: left; font-family: Arial, sans-serif;\">\n  <thead>\n    <tr style=\"background-color: #f2f2f2;\">\n      <th style=\"width: 25%;\">Property</th>\n      <th style=\"width: 25%;\">Solids</th>\n      <th style=\"width: 25%;\">Liquids</th>\n      <th style=\"width: 25%;\">Gases</th>\n    </tr>\n  </thead>\n  <tbody>\n    <tr>\n      <td><strong>Molecular Arrangement</strong></td>\n      <td>The molecules of a solid are very tightly packed.</td>\n      <td>The molecules of a liquid are loosely packed.</td>\n      <td>The molecules of a gas are far separated from each other.</td>\n    </tr>\n    <tr>\n      <td><strong>Intermolecular Spacing</strong></td>\n      <td>The intermolecular spacing is the least in solids.</td>\n      <td>The intermolecular spacing in liquids is more than that in solids but less than that in gases.</td>\n      <td>The intermolecular spacing is the maximum in gases.</td>\n    </tr>\n    <tr>\n      <td><strong>Intermolecular Force</strong></td>\n      <td>The intermolecular force is the strongest in solids.</td>\n      <td>The intermolecular force in liquids is stronger than that in gases but weaker than that in solids.</td>\n      <td>The intermolecular force is the weakest in gases.</td>\n    </tr>\n    <tr>\n      <td><strong>Molecular Motion</strong></td>\n      <td>Molecules of a solid possess vibratory motion of very small amplitude.</td>\n      <td>Molecules of a liquid possess random motion within the boundary of the liquid.</td>\n      <td>Molecules of a gas possess random motion in the whole volume of the containing vessel.</td>\n    </tr>\n  </tbody>\n</table>","teacherTip":"","examTip":""},{"id":"pqb-ch1-matter-12","topicId":"ch1-matter","type":"short_answer","subtopic":"Additional Questions","question":"2) Differentiate between cohesive force and adhesive force with examples.","answer":"<table border=\"1\" cellpadding=\"8\" cellspacing=\"0\" style=\"border-collapse: collapse; width: 100%; text-align: left; font-family: Arial, sans-serif;\">\n  <thead>\n    <tr style=\"background-color: #f2f2f2;\">\n      <th style=\"width: 20%;\">Type of Force</th>\n      <th style=\"width: 40%;\">Definition</th>\n      <th style=\"width: 40%;\">Examples</th>\n    </tr>\n  </thead>\n  <tbody>\n    <tr>\n      <td><strong>Cohesive Force</strong></td>\n      <td>The force of attraction between similar kinds of molecules.</td>\n      <td>\n        <ul>\n          <li>Molecules of mercury remaining sticking to each other in a drop of mercury.</li>\n          <li>Molecules of iron sticking to each other in a piece of iron.</li>\n        </ul>\n      </td>\n    </tr>\n    <tr>\n      <td><strong>Adhesive Force</strong></td>\n      <td>The force of attraction between different kinds of molecules.</td>\n      <td>\n        <ul>\n          <li>The force of attraction between paper and glue.</li>\n          <li>The force of attraction between paper and ink.</li>\n          <li>The force of attraction between cement and brick.</li>\n        </ul>\n      </td>\n    </tr>\n  </tbody>\n</table>","teacherTip":"","examTip":""},{"id":"pqb-ch1-matter-19","topicId":"ch1-matter","type":"short_answer","subtopic":"Additional Questions","question":"9)Write one difference between gas and vapor.","answer":"<!DOCTYPE html>\n<html lang=\"en\">\n<head>\n    <meta charset=\"UTF-8\">\n    <meta name=\"viewport\" content=\"width=device-width, initial-scale=1.0\">\n    <title>Difference Between Gas and Vapor</title>\n    <style>\n        body {\n            font-family: -apple-system, BlinkMacSystemFont, \"Segoe UI\", Roboto, Helvetica, Arial, sans-serif;\n            line-height: 1.6;\n            color: #333;\n            max-width: 800px;\n            margin: 20px auto;\n            padding: 0 15px;\n        }\n        h2 {\n            color: #2c3e50;\n            border-bottom: 2px solid #ecf0f1;\n            padding-bottom: 8px;\n            margin-top: 30px;\n        }\n        table {\n            width: 100%;\n            border-collapse: collapse;\n            margin: 20px 0;\n            font-size: 16px;\n        }\n        th, td {\n            border: 1px solid #dcdde1;\n            padding: 12px 15px;\n            text-align: left;\n        }\n        th {\n            background-color: #f5f6fa;\n            color: #2c3e50;\n            font-weight: 600;\n        }\n        tr:nth-child(even) {\n            background-color: #fbfbfc;\n        }\n        .feature-cell {\n            font-weight: 600;\n            color: #34495e;\n            width: 20%;\n        }\n        blockquote {\n            background: #f8f9fa;\n            border-left: 4px solid #3498db;\n            margin: 1.5em 10px;\n            padding: 0.5em 15px;\n            font-style: italic;\n        }\n    </style>\n</head>\n<body>\n\n    <table>\n        <thead>\n            <tr>\n                <th>Feature</th>\n                <th>Gas</th>\n                <th>Vapor</th>\n            </tr>\n        </thead>\n        <tbody>\n            <tr>\n                <td class=\"feature-cell\">Definition</td>\n                <td>A substance that exists naturally in the gaseous state at standard room temperature and pressure (e.g., Oxygen, Nitrogen).</td>\n                <td>The gaseous state of a substance that is normally a solid or liquid at room temperature (e.g., Water vapor, Iodine vapor).</td>\n            </tr>\n            <tr>\n                <td class=\"feature-cell\">Thermodynamic State</td>\n                <td>It is above its critical temperature. It cannot be liquefied by pressure alone, no matter how much pressure is applied.</td>\n                <td>It is below its critical temperature. It can be condensed back into a liquid or solid simply by increasing the pressure.</td>\n            </tr>\n        </tbody>\n    </table>\n\n    <h2>Summary for an Exam/Test</h2>\n    <p>If you need a quick, one-line difference for an assessment, you can write:</p>\n    <blockquote>\n        \"A gas is a substance that exists naturally in the gaseous state at room temperature, whereas a vapor is the gaseous form of a substance that is normally a liquid or solid at room temperature.\"\n    </blockquote>\n\n</body>\n</html>","teacherTip":"","examTip":""},{"id":"phy-s1-sec_01","topicId":"ch1-matter","type":"note","subtopic":"1. Matter, Molecules, Cohesion and Adhesion","content":"**Executive summary:** Matter is anything that has mass and occupies space; it exists in three main forms — solid, liquid and gas. The **molecule** is the smallest independent unit showing all properties of a substance. **Cohesion** (same substance) and **adhesion** (different substances) are the two intermolecular attractions; their strength depends on the nature of the molecules and the distance between them.\n\n**Must know**\n• **Matter** = has mass + occupies space. Examples: iron, water, air, plastic, wood, stone, oil, steam.\n• Matter is composed of **elements**. One kind of element only → smallest unit = **atom**. Two or more elements combined → smallest unit = **molecule**.\n• A molecule may consist of one or more atoms: a **water** molecule = 2 hydrogen atoms + 1 oxygen atom; a **common salt** molecule = 1 sodium atom + 1 chlorine atom.\n• Molecules exert forces on one another — these **intermolecular forces** are responsible for various properties of a substance.\n• Molecules are in a state of **continuous motion** and thus possess energy.\n• **Force of cohesion (cohesive force)**: intermolecular attraction amongst molecules of the **same** substance.\n• **Force of adhesion (adhesive force)**: attraction between molecules of **different** substances — it makes substances stick to surfaces (paint adhering to a wall or door).\n• The **magnitude** of intermolecular force depends on (1) the **nature** of the molecules and (2) the **intermolecular distance**. It is **strongest in solids, weakest in gases**.\n\n**Activity evidence (hammer test):** beat chalk, brick and iron with a hammer — chalk powders easily, brick breaks with difficulty, iron hardly breaks. Conclusion: cohesion exists in all, but **chalk < brick << iron**.\n• Tearing a sheet of paper = doing work **against the force of cohesion** between paper molecules.","explanation":"**📊 Chart — Cohesion vs Adhesion**\n| Criterion | Cohesion | Adhesion |\n|---|---|---|\n| Acts between | Molecules of the **same** substance | Molecules of **different** substances |\n| Examples | Water drops merging; tearing paper needs work against it | Paint sticking to a wall; glue–paper; ink–paper |\n| Strength comparison | Chalk (weak) < brick < iron (very strong) | Decides how well liquids wet surfaces |\n| Exam trap | 'Adhesion acts in the same substance' = FALSE | Painting a wall uses adhesion, not cohesion |\n\n**Cornell cues (self-test):**\n• Define matter and give four examples.\n• How many atoms of which elements make one water molecule? One salt molecule?\n• Which force do you work against while tearing paper?\n• On what two factors does the magnitude of intermolecular force depend?\n• In which state is intermolecular force strongest and in which weakest?\n\n**Definitions / Exam traps:**\n• Atom = smallest unit of an ELEMENT; molecule = smallest unit of MATTER that exists independently with all its properties.\n• The hammer activity compares COHESION, not hardness for its own sake.","source":"icse","examTip":"Cohesion = same substance, adhesion = different substances — and remember the two factors controlling their magnitude: nature of molecules and intermolecular distance.","linkedMcqCount":9},{"id":"phy-s1-sec_02","topicId":"ch1-matter","type":"note","subtopic":"2. The Three States of Matter — Molecular Arrangement","content":"**Executive summary:** The properties of solids, liquids and gases follow from three molecular quantities: packing (intermolecular space), force strength, and type of motion. Solids: vibration only → fixed shape. Liquids: molecules slide within the liquid → fixed volume, free surface, no fixed shape. Gases: independent motion → no fixed shape or volume.\n\n**Solids**\n• Molecules **closely packed**; intermolecular spaces **extremely small**.\n• Intermolecular forces **very strong** → positions of molecules **fixed** → definite **volume AND shape**.\n• Molecules can have only **vibrational motion**.\n• Cannot be compressed (close packing) → solids are **hard and rigid**; cannot flow; can be stored **without a vessel**.\n\n**Liquids**\n• Molecules **less tightly packed**; spaces somewhat more than solids.\n• Forces **weak** → positions not fixed → **no shape of its own**, can **flow**.\n• Forces still do not let molecules leave the liquid easily → **definite volume**; has a **definite free surface**.\n• Can be **compressed only a little**; stored in a container.\n• **Activity (sugar in brim-full glass):** sugar dissolves WITHOUT water spilling → liquids have **intermolecular spaces** into which sugar molecules enter.\n\n**Gases**\n• Molecules **far apart**; intermolecular space much larger than liquids.\n• Forces **extremely weak / almost zero** → each molecule moves **independently** → neither definite shape nor definite volume; can be stored **only in a closed vessel**.\n• Can be **compressed easily**; flows very easily; has **no free surface** of its own.\n• **Activity (incense sticks/scent):** the smell spreads through the whole room — gas molecules move freely everywhere.","explanation":"**📊 Chart — Table 1.1: the five differences (molecular concept)**\n| Property | Solids | Liquids | Gases |\n|---|---|---|---|\n| Packing / space | Closely packed; space extremely small | Less tight; space more than solids | No packing; space very large |\n| Intermolecular force | Very strong | Weak | Almost zero |\n| Position / shape / volume | Fixed positions → finite shape & size | Not fixed → no shape, finite volume | Independent → no shape, no volume |\n| Motion of molecules | Vibrational only | Move inside liquid; cannot leave surface | Random translational motion |\n| Compressibility | Cannot be compressed | Slightly compressible | Easily compressed |\n\n**Cornell cues (self-test):**\n• Why can't a solid flow?\n• Why does a liquid have a definite volume but not a definite shape?\n• Which state has a free surface? Which has none?\n• What does the sugar-in-full-glass activity prove?\n• Why must a gas be kept in a CLOSED vessel?\n\n**Definitions / Exam traps:**\n• 'Liquids and solids are closely packed' — liquids are LESS tightly packed than solids.\n• 'A gas cannot be compressed' — FALSE; gases compress most easily.\n• A liquid has a definite FREE SURFACE; a gas has none.","source":"icse","examTip":"Reproduce the five-row table from memory — every line of it appears somewhere as a fill-blank, T/F or match question.","linkedMcqCount":18},{"id":"phy-s1-sec_03","topicId":"ch1-matter","type":"note","subtopic":"3. Kinetic Theory of Matter and Energy of Molecules","content":"**Executive summary:** The kinetic (molecular) theory — developed about **200 years ago** by **Dalton, Joule, Davy, Maxwell, Boltzmann** and others — explains all properties of matter in terms of moving molecules. Molecular energy is **minimum in solids** (vibration only), more in liquids, **maximum in gases**; the average kinetic energy of molecules is the measure of **temperature**.\n\n**Main points of the kinetic theory**\n• Everything is composed of very small particles — **molecules**.\n• Molecules of one substance are **identical in shape, size and mass**; molecules of **different** substances differ in mass, shape, size and composition.\n• Molecules are **continuously in random motion**; the type of motion differs in different states.\n• Molecular motion **increases with temperature** and decreases as temperature falls.\n• Because of this motion, molecules possess **kinetic energy**, which **increases with temperature**.\n• Molecules have **intermolecular spaces** — maximum in gases, minimum in solids.\n• Molecules attract each other: **cohesion** (same substance) and **adhesion** (different substances).\n• Intermolecular forces are **strongest in solids, weakest in gases**.\n• **Activity (ink in water):** a drop of ink spreads until the water is uniformly coloured — molecules are in a state of motion.\n\n**Energy of molecules in the three states**\n• **Solids:** molecules can only **vibrate to and fro about their mean positions** → energy of movement is **minimum**. At low temperature the **amplitude of vibration is small**; heating increases the amplitude and kinetic energy. At the **melting point**, KE becomes sufficient to overcome intermolecular forces — molecules leave their fixed positions and the solid becomes liquid.\n• **Liquids:** molecules move freely **within** the liquid but cannot leave its free surface → KE greater than in solids. On heating, KE keeps rising; at the **boiling point** the energy is enough to overcome mutual attraction — the liquid becomes gas.\n• **Gases:** molecules have **independent translatory motion in all directions** through space → KE is **maximum**. The translational KE increases further on heating.","explanation":"**📊 Chart — Motion and energy ladder**\n| State | Type of motion | Energy of molecules |\n|---|---|---|\n| Solid | Vibration about fixed mean positions | Minimum |\n| Liquid | Free movement within the liquid (cannot leave surface) | Intermediate |\n| Gas | Independent translatory motion in all directions | Maximum |\n\n**Cornell cues (self-test):**\n• Name four scientists who developed the kinetic theory. How old is it?\n• State three main points of the kinetic theory.\n• What happens to the amplitude of vibration of solid molecules on heating?\n• At which temperature does molecular KE first overcome intermolecular force in a solid? In a liquid?\n• What does the ink-drop activity demonstrate?\n\n**Definitions / Exam traps:**\n• The **average kinetic energy** of molecules is a measure of the substance's **temperature**.\n• 'Molecules of the whole universe are identical' — FALSE; only molecules of the SAME substance are identical.\n• In liquids, molecules cannot LEAVE the surface (that needs boiling-point energy or evaporation from the surface).","source":"icse","examTip":"Quote scientists' names (Dalton, Joule, Maxwell, Boltzmann) and '200 years ago' — direct fill-blank material — and keep the energy order solid < liquid < gas ready.","linkedMcqCount":9},{"id":"phy-s1-sec_04","topicId":"ch1-matter","type":"note","subtopic":"4. Change of State: Six Processes, Latent Heat and Kinetic Explanation","content":"**Executive summary:** Change of state = changing a substance from one physical state to another **by changing its temperature**. Six processes: melting/fusion, freezing/solidification, vaporisation/boiling, condensation/liquefaction, sublimation, deposition. At every change of state the **temperature stays constant** — the heat exchanged is **latent heat**, which changes the **potential energy** (separation) of molecules, not their kinetic energy.\n\n**The six processes (all at a FIXED temperature)**\n• **Melting (fusion):** solid → liquid on heating, at the **melting point**. Ice melts at **0 °C**; wax at **55 °C**. Latent heat of fusion of ice = **80 cal/g = 3.35 × 10⁵ J/kg**.\n• **Freezing (solidification):** liquid → solid on cooling, at the **freezing point**. For a given substance **freezing point = melting point** (water/ice: 0 °C). Freezing point of mercury = **−39 °C**; of molten wax = **55 °C**. Water releases **80 cal/g** on freezing — latent heat of freezing equals latent heat of fusion.\n• **Vaporisation (boiling):** liquid → gas on heating, at the **boiling point**. Water boils at **100 °C**; alcohol at **78 °C**. Latent heat of vaporisation of water = **540 cal/g = 2.26 × 10⁶ J/kg**.\n• **Condensation (liquefaction):** gas → liquid on cooling, at the **condensation/liquefaction point**, which equals the boiling point (steam condenses at 100 °C). The substance releases exactly the heat absorbed during boiling — steam gives out 540 cal/g, which is why **steam burns are more severe than boiling-water burns**.\n• **Sublimation:** solid → vapour DIRECTLY (no liquid stage), at the **sublimation point**; the solid absorbs **latent heat of sublimation**. Solids that sublime are **sublimates**; their vapour is the **sublime**. Examples: **naphthalene balls** (moth balls shrinking in the cupboard), **ammonium chloride, iodine, camphor, dry ice**.\n• **Deposition (desublimation):** vapour → solid directly on cooling; heat is **released**. Examples: **snowfall** in hilly regions (cloud vapour → snowflakes directly) and **hoarfrost** on plants in extreme winter nights.\n\n**Key activities**\n• **Ice–water–steam:** ice at 0 °C stays at 0 °C while melting; the water then warms to 100 °C and stays at 100 °C while boiling — two temperature plateaus.\n• **Melting point of wax / boiling point of water:** in both, the thermometer reading becomes CONSTANT when the change of state begins — that constant reading IS the melting/boiling point.\n• **Ammonium chloride:** heated in a china dish under an inverted funnel (cotton plug in stem) — vapours rise (sublimation) and solidify as a thin layer on the cool funnel wall (deposition).\n\n**Kinetic-theory explanation**\n• **Melting:** heating makes solid molecules vibrate more violently; at the melting point they gain enough energy to overcome intermolecular attraction and move within the substance. The heat absorbed does NOT raise temperature — it does work against attraction to increase molecular separation.\n• **Boiling:** liquid molecules' KE rises with heating; at the boiling point they overcome attraction, **leave the liquid surface** and move freely in space.\n• **Sublimation:** in some solids the intermolecular forces are **comparatively weak**; heating raises molecular KE rapidly and at the sublimation point molecules break free directly. (This is also why **not all solids sublime** — most have forces too strong to skip the liquid stage.)\n• Ordinarily heat raises the **average KE** (temperature rises); during change of state, heat changes the **potential energy** of molecules instead → temperature constant → hence the name **latent** ('hidden') heat.\n\n**Dry ice:** solid carbon dioxide — looks like ice, sublimes directly to gas; used as a **refrigerant** for transporting perishable foods, meat and fish.","explanation":"**📊 Chart — Reference data (memorise)**\n| Melting points (°C) | | Boiling points (°C) | |\n|---|---|---|---|\n| Ice 0 | Lead 327 | Water 100 | Ether 34.5 |\n| Paraffin wax 55 | Aluminium 658 | Alcohol 78.5 | Mercury 357 |\n| Naphthalene 80 | Silver 961, Copper 1083 | | |\n\n**📊 Chart — 'Something More' facts**\n| About melting point | About boiling point |\n|---|---|\n| Constant for a pure solid | Fixed for a pure liquid |\n| No two pure solids share the same MP | No two pure liquids share the same BP |\n| Changes with atmospheric pressure | INCREASES with pressure (pressure-cooker principle), decreases at low pressure |\n| Changes with impurities (salt lowers ice's MP — used in making kulfi) | Changes with impurities |\n\n**Cornell cues (self-test):**\n• Name all six changes of state and the direction of each.\n• Why does temperature stay constant during melting? Where does the heat go?\n• Latent heat of fusion of ice and of vaporisation of water — values in cal/g and J/kg?\n• Why are steam burns worse than boiling-water burns?\n• Why do only SOME solids sublime? Name four sublimates.\n• What is dry ice and its main use?\n• How does a pressure cooker exploit the boiling point–pressure relation?\n\n**Definitions / Exam traps:**\n• Latent heat = heat supplied/released during change of state at CONSTANT temperature.\n• 'Water at 100 °C has more heat energy than steam at 100 °C' — FALSE; steam carries extra latent heat.\n• 'Gas → solid directly is sublimation' — FALSE; that is DEPOSITION (sublimation is solid → gas).\n• Common salt does NOT sublime.\n• On a temperature–time heating graph, every FLAT (horizontal) portion is a change of state; the first plateau's temperature is the melting point.","source":"icse","examTip":"Latent heat changes potential energy, never kinetic — say this line whenever a 'temperature stays constant' question appears, and quote 80 cal/g and 540 cal/g with their J/kg twins.","linkedMcqCount":25},{"id":"c-1781234542401","topicId":"ch1-matter","type":"note","subtopic":"Kinetic theory of matter","content":"<!DOCTYPE html>\n<html lang=\"en\">\n<head>\n    <meta charset=\"UTF-8\">\n    <meta name=\"viewport\" content=\"width=device-width, initial-scale=1.0\">\n    <title>Pioneers of the Kinetic Theory</title>\n    <style>\n        :root {\n            --bg-gradient-start: #f8fafc;\n            --bg-gradient-end: #e2e8f0;\n            --card-bg: #ffffff;\n            --text-main: #0f172a;\n            --text-muted: #475569;\n            --primary: #2563eb;\n            --primary-light: #eff6ff;\n            --secondary: #0d9488;\n            --secondary-light: #f0fdfa;\n            --accent: #7c3aed;\n            --border: #cbd5e1;\n            --table-header: #1e293b;\n        }\n\n        body {\n            font-family: 'Segoe UI', system-ui, -apple-system, sans-serif;\n            background: linear-gradient(135deg, var(--bg-gradient-start), var(--bg-gradient-end));\n            color: var(--text-main);\n            line-height: 1.6;\n            margin: 0;\n            padding: 2rem 1rem;\n            display: flex;\n            justify-content: center;\n        }\n\n        .container {\n            max-width: 900px;\n            width: 100%;\n        }\n\n        .main-card {\n            background: var(--card-bg);\n            border-radius: 24px;\n            padding: 3rem;\n            box-shadow: 0 10px 30px rgba(15, 23, 42, 0.08);\n            border: 1px solid rgba(255, 255, 255, 0.7);\n        }\n\n        header {\n            text-align: center;\n            margin-bottom: 2.5rem;\n            padding-bottom: 1.5rem;\n            border-bottom: 2px dashed var(--border);\n        }\n\n        h1 {\n            font-size: 2.2rem;\n            color: var(--text-main);\n            margin: 0 0 0.5rem 0;\n            font-weight: 800;\n        }\n\n        h1 span {\n            color: var(--primary);\n        }\n\n        .tagline {\n            font-size: 1.1rem;\n            color: var(--text-muted);\n            margin: 0;\n        }\n\n        /* Summary Box */\n        .summary-box {\n            background-color: var(--primary-light);\n            border-left: 5px solid var(--primary);\n            padding: 1.5rem;\n            border-radius: 12px;\n            margin-bottom: 2.5rem;\n            font-size: 1.05rem;\n            color: #1e40af;\n        }\n\n        /* Table Styling */\n        .table-responsive {\n            overflow-x: auto;\n            border-radius: 12px;\n            border: 1px solid var(--border);\n            box-shadow: 0 4px 6px -1px rgba(0,0,0,0.05);\n            margin-bottom: 2rem;\n        }\n\n        table {\n            width: 100%;\n            border-collapse: collapse;\n            text-align: left;\n            font-size: 1rem;\n        }\n\n        th {\n            background-color: var(--table-header);\n            color: #ffffff;\n            font-weight: 700;\n            padding: 1.25rem 1rem;\n            letter-spacing: 0.05em;\n            text-transform: uppercase;\n            font-size: 0.9rem;\n        }\n\n        td {\n            padding: 1.25rem 1rem;\n            border-bottom: 1px solid var(--border);\n            vertical-align: top;\n        }\n\n        tr:last-child td {\n            border-bottom: none;\n        }\n\n        tr:nth-child(even) {\n            background-color: #f8fafc;\n        }\n\n        .scientist-name {\n            font-weight: 800;\n            color: var(--primary);\n            font-size: 1.1rem;\n            display: block;\n            margin-bottom: 0.25rem;\n        }\n\n        .era-tag {\n            display: inline-block;\n            font-size: 0.8rem;\n            background-color: #e2e8f0;\n            color: var(--text-muted);\n            padding: 0.2rem 0.5rem;\n            border-radius: 4px;\n            font-weight: 600;\n        }\n\n        .keyword {\n            font-weight: 700;\n            color: var(--secondary);\n        }\n\n        /* Timeline Connection */\n        .timeline-note {\n            background-color: var(--secondary-light);\n            border: 1px solid #ccfbf1;\n            border-radius: 12px;\n            padding: 1.5rem;\n            text-align: center;\n            color: #115e59;\n            font-weight: 500;\n        }\n\n        @media (max-width: 600px) {\n            .main-card { padding: 1.5rem; }\n            th, td { padding: 1rem 0.75rem; font-size: 0.95rem; }\n        }\n    </style>\n</head>\n<body>\n\n<div class=\"container\">\n    <div class=\"main-card\">\n        <header>\n            <h1>Architects of the <span>Kinetic Theory</span></h1>\n            <p class=\"tagline\">How 200 years of physics transformed heat from a \"fluid\" into molecular motion</p>\n        </header>\n\n        <div class=\"summary-box\">\n            <strong>The Historical Shift:</strong> Before these scientists, heat was widely believed to be an invisible fluid called \"caloric\" that flowed between objects. The combined works of Dalton, Davy, Joule, Maxwell, and Boltzmann dismantled this idea, proving that matter is made of tiny particles and that heat is simply the <strong>kinetic energy</strong> of their continuous random motion.\n        </div>\n\n        \n\n        <div class=\"table-responsive\">\n            <table>\n                <thead>\n                    <tr>\n                        <th style=\"width: 25%;\">Scientist</th>\n                        <th style=\"width: 25%;\">Core Concept</th>\n                        <th style=\"width: 50%;\">Contribution to Kinetic Theory</th>\n                    </tr>\n                </thead>\n                <tbody>\n                    <tr>\n                        <td>\n                            <span class=\"scientist-name\">John Dalton</span>\n                            <span class=\"era-tag\">Early 1800s</span>\n                        </td>\n                        <td><span class=\"keyword\">Atomic Theory</span></td>\n                        <td>Provided the structural foundation. By proving that matter consists of discrete, indivisible particles (atoms/molecules), he gave the kinetic theory the physical \"billiard balls\" it needed to explain microscopic motion and collisions.</td>\n                    </tr>\n                    <tr>\n                        <td>\n                            <span class=\"scientist-name\">Humphry Davy</span>\n                            <span class=\"era-tag\">Late 1700s / Early 1800s</span>\n                        </td>\n                        <td><span class=\"keyword\">Heat as Motion</span></td>\n                        <td>Conducted the famous friction experiment of rubbing two pieces of ice together to melt them in a vacuum. He demonstrated that heat could be generated entirely by friction, heavily striking down the \"caloric fluid\" theory and proving heat is microscopic motion.</td>\n                    </tr>\n                    <tr>\n                        <td>\n                            <span class=\"scientist-name\">James Prescott Joule</span>\n                            <span class=\"era-tag\">Mid 1800s</span>\n                        </td>\n                        <td><span class=\"keyword\">Mechanical Equivalent of Heat</span></td>\n                        <td>Mathematically and experimentally proved that mechanical work directly converts into heat energy. This cemented the First Law of Thermodynamics and verified that heating a gas simply means adding kinetic energy to its molecules.</td>\n                    </tr>\n                    <tr>\n                        <td>\n                            <span class=\"scientist-name\">James Clerk Maxwell</span>\n                            <span class=\"era-tag\">Mid-to-Late 1800s</span>\n                        </td>\n                        <td><span class=\"keyword\">Statistical Averages</span></td>\n                        <td>Recognized that gas molecules do not all move at the same speed. He formulated a statistical distribution showing the range of molecular speeds at a given temperature, linking macroscopic temperature directly to average microscopic velocity.</td>\n                    </tr>\n                    <tr>\n                        <td>\n                            <span class=\"scientist-name\">Ludwig Boltzmann</span>\n                            <span class=\"era-tag\">Late 1800s</span>\n                        </td>\n                        <td><span class=\"keyword\">Statistical Mechanics</span></td>\n                        <td>Expanded Maxwell's work into the Maxwell-Boltzmann distribution. He mathematically linked the chaotic, random motion of individual molecules to macroscopic properties like entropy and pressure, completing the modern Kinetic Theory of Gases.</td>\n                    </tr>\n                </tbody>\n            </table>\n        </div>\n\n        <div class=\"timeline-note\">\n            💡 <strong>Evolution of a Theory:</strong> It started with the <em>structure</em> (Dalton), moved to the <em>concept of motion and energy</em> (Davy & Joule), and was finally perfected with complex <em>mathematics and statistics</em> (Maxwell & Boltzmann).\n        </div>\n\n    </div>\n</div>\n\n</body>\n</html>","explanation":"","teacherTip":"","examTip":""}],"deletedContentIds":["phy-s1-q001","phy-s1-q002","phy-s1-q003","phy-s1-q005","phy-s1-q053","phy-s1-q047"],"editedContentIds":["phy-s1-sec_01","phy-s1-sec_02","phy-s1-sec_03","phy-s1-sec_04","pqb-ch1-matter-11","pqb-ch1-matter-12","pqb-ch1-matter-19"],"progress":{"b1tf1":{"attempts":2,"correct":2,"lastResult":"correct","lastAt":"2026-06-10T12:35:50.640Z","guessed":false,"streak":1,"srsNextAt":null,"srsLevel":0},"b1tf2":{"attempts":2,"correct":2,"lastResult":"correct","lastAt":"2026-06-10T12:36:12.057Z","guessed":false,"streak":1,"srsNextAt":null,"srsLevel":0},"b1tf3":{"attempts":3,"correct":2,"lastResult":"correct","lastAt":"2026-06-10T12:36:25.357Z","guessed":false,"streak":1,"srsNextAt":"2026-06-13T12:36:25.357Z","srsLevel":1},"b1fb1":{"attempts":2,"correct":2,"lastResult":"correct","lastAt":"2026-06-10T08:36:55.265Z"},"b1fb2":{"attempts":1,"correct":0,"lastResult":"wrong","lastAt":"2026-06-10T08:37:44.165Z"},"b1fb3":{"attempts":1,"correct":1,"lastResult":"correct","lastAt":"2026-06-10T08:38:03.464Z"},"b3kb-sa17":{"attempts":1,"correct":0,"lastResult":"seen","lastAt":"2026-06-10T09:17:28.272Z"},"b3kb-sa16":{"attempts":1,"correct":0,"lastResult":"seen","lastAt":"2026-06-10T09:17:30.823Z"},"b1x-mcq6":{"attempts":1,"correct":1,"lastResult":"correct","lastAt":"2026-06-10T10:38:35.936Z"},"b1tf4":{"attempts":1,"correct":1,"lastResult":"correct","lastAt":"2026-06-10T12:36:29.956Z","guessed":false,"streak":1,"srsNextAt":null,"srsLevel":0},"b1mcq1":{"attempts":1,"correct":1,"lastResult":"correct","lastAt":"2026-06-10T12:37:05.273Z","guessed":false,"streak":1,"srsNextAt":null,"srsLevel":0},"b1mcq2":{"attempts":1,"correct":1,"lastResult":"correct","lastAt":"2026-06-10T12:37:10.788Z","guessed":false,"streak":1,"srsNextAt":null,"srsLevel":0},"b1ocr-mcq1":{"attempts":1,"correct":1,"lastResult":"correct","lastAt":"2026-06-10T12:37:19.455Z","guessed":false,"streak":1,"srsNextAt":null,"srsLevel":0},"b1ocr-mcq2":{"attempts":1,"correct":1,"lastResult":"correct","lastAt":"2026-06-10T12:37:26.821Z","guessed":false,"streak":1,"srsNextAt":null,"srsLevel":0},"b1ocr-mcq3":{"attempts":1,"correct":1,"lastResult":"correct","lastAt":"2026-06-10T12:37:38.555Z","guessed":false,"streak":1,"srsNextAt":null,"srsLevel":0},"b1ocr-mcq4":{"attempts":1,"correct":0,"lastResult":"wrong","lastAt":"2026-06-10T12:37:44.588Z","guessed":false,"streak":0,"srsNextAt":"2026-06-11T12:37:44.588Z","srsLevel":0},"b1ocr-mcq5":{"attempts":1,"correct":1,"lastResult":"correct","lastAt":"2026-06-10T12:38:29.437Z","guessed":false,"streak":1,"srsNextAt":null,"srsLevel":0},"b1ocr-mcq6":{"attempts":1,"correct":0,"lastResult":"wrong","lastAt":"2026-06-10T12:38:52.720Z","guessed":false,"streak":0,"srsNextAt":"2026-06-11T12:38:52.720Z","srsLevel":0},"b1ocr-mcq8":{"attempts":1,"correct":1,"lastResult":"correct","lastAt":"2026-06-10T12:39:03.536Z","guessed":false,"streak":1,"srsNextAt":null,"srsLevel":0},"b1ocr-mcq9":{"attempts":2,"correct":1,"lastResult":"correct","lastAt":"2026-06-10T12:39:10.903Z","guessed":false,"streak":1,"srsNextAt":"2026-06-13T12:39:10.903Z","srsLevel":1},"b1ocr-mcq10":{"attempts":1,"correct":1,"lastResult":"correct","lastAt":"2026-06-10T12:39:47.585Z","guessed":false,"streak":1,"srsNextAt":null,"srsLevel":0},"b1ocr-csq1":{"attempts":2,"correct":1,"lastResult":"correct","lastAt":"2026-06-10T12:40:12.889Z","guessed":false,"streak":1,"srsNextAt":"2026-06-13T12:40:12.889Z","srsLevel":1},"b1ocr-csq2":{"attempts":1,"correct":1,"lastResult":"correct","lastAt":"2026-06-10T12:40:23.801Z","guessed":false,"streak":1,"srsNextAt":null,"srsLevel":0},"b1ocr-csq3":{"attempts":1,"correct":0,"lastResult":"wrong","lastAt":"2026-06-10T12:40:34.702Z","guessed":false,"streak":0,"srsNextAt":"2026-06-11T12:40:34.702Z","srsLevel":0},"b1ocr-cfq1":{"attempts":1,"correct":1,"lastResult":"correct","lastAt":"2026-06-10T12:42:18.299Z","guessed":false,"streak":1,"srsNextAt":null,"srsLevel":0},"b1ocr-cfq2":{"attempts":1,"correct":1,"lastResult":"correct","lastAt":"2026-06-10T12:42:54.232Z","guessed":false,"streak":1,"srsNextAt":null,"srsLevel":0},"b1ocr-cfq3":{"attempts":1,"correct":1,"lastResult":"correct","lastAt":"2026-06-10T12:43:43.047Z","guessed":true,"streak":0,"srsNextAt":"2026-06-11T12:43:43.047Z","srsLevel":0},"tf3":{"attempts":3,"correct":2,"lastResult":"wrong","lastAt":"2026-06-10T19:56:07.077Z","guessed":false,"streak":0,"srsNextAt":"2026-06-11T19:56:07.077Z","srsLevel":0},"tf4":{"attempts":1,"correct":1,"lastResult":"correct","lastAt":"2026-06-10T19:56:16.577Z","guessed":false,"streak":1,"srsNextAt":null,"srsLevel":0},"tf5":{"attempts":2,"correct":2,"lastResult":"correct","lastAt":"2026-06-10T20:02:14.974Z","guessed":false,"streak":2,"srsNextAt":null,"srsLevel":0},"tf6":{"attempts":1,"correct":1,"lastResult":"correct","lastAt":"2026-06-10T19:56:38.211Z","guessed":false,"streak":1,"srsNextAt":null,"srsLevel":0},"tf7":{"attempts":1,"correct":1,"lastResult":"correct","lastAt":"2026-06-10T19:56:47.077Z","guessed":false,"streak":1,"srsNextAt":null,"srsLevel":0},"tf8":{"attempts":1,"correct":1,"lastResult":"correct","lastAt":"2026-06-10T19:56:59.377Z","guessed":false,"streak":1,"srsNextAt":null,"srsLevel":0},"tf9":{"attempts":1,"correct":1,"lastResult":"correct","lastAt":"2026-06-10T20:00:02.892Z","guessed":false,"streak":1,"srsNextAt":null,"srsLevel":0},"tf10":{"attempts":1,"correct":1,"lastResult":"correct","lastAt":"2026-06-10T20:00:17.380Z","guessed":false,"streak":1,"srsNextAt":null,"srsLevel":0},"sa-sd5":{"attempts":1,"correct":0,"lastResult":"seen","lastAt":"2026-06-10T20:02:51.641Z","guessed":false,"streak":0,"srsNextAt":null,"srsLevel":0},"sa-se1":{"attempts":1,"correct":0,"lastResult":"seen","lastAt":"2026-06-10T20:03:03.712Z","guessed":false,"streak":0,"srsNextAt":null,"srsLevel":0},"sa-se2":{"attempts":1,"correct":0,"lastResult":"seen","lastAt":"2026-06-10T20:03:17.495Z","guessed":false,"streak":0,"srsNextAt":null,"srsLevel":0},"phy-s1-q004":{"attempts":1,"correct":0,"lastResult":"wrong","lastAt":"2026-06-10T20:23:19.381Z","guessed":false,"streak":0,"srsNextAt":"2026-06-11T20:23:19.381Z","srsLevel":0},"phy-s1-q006":{"attempts":1,"correct":0,"lastResult":"wrong","lastAt":"2026-06-10T20:29:06.826Z","guessed":false,"streak":0,"srsNextAt":"2026-06-11T20:29:06.826Z","srsLevel":0},"phy-s1-q127":{"attempts":2,"correct":1,"lastResult":"correct","lastAt":"2026-06-11T04:11:36.042Z","guessed":false,"streak":1,"srsNextAt":"2026-06-14T04:11:36.042Z","srsLevel":1},"phy-s1-q085":{"attempts":1,"correct":0,"lastResult":"wrong","lastAt":"2026-06-11T04:11:06.541Z","guessed":false,"streak":0,"srsNextAt":"2026-06-12T04:11:06.542Z","srsLevel":0},"phy-s1-q094":{"attempts":1,"correct":0,"lastResult":"wrong","lastAt":"2026-06-11T04:30:38.972Z","guessed":false,"streak":0,"srsNextAt":"2026-06-12T04:30:38.972Z","srsLevel":0},"ch3sa1":{"attempts":1,"correct":0,"lastResult":"seen","lastAt":"2026-06-11T04:40:21.329Z","guessed":false,"streak":0,"srsNextAt":null,"srsLevel":0},"phy-s1-q053":{"attempts":1,"correct":1,"lastResult":"correct","lastAt":"2026-06-11T10:40:53.939Z","guessed":false,"streak":1,"srsNextAt":null,"srsLevel":0},"neet-s4-q150":{"attempts":1,"correct":0,"lastResult":"wrong","lastAt":"2026-06-11T10:45:00.811Z","guessed":false,"streak":0,"srsNextAt":"2026-06-12T10:45:00.811Z","srsLevel":0},"ch1ar1":{"attempts":1,"correct":1,"lastResult":"correct","lastAt":"2026-06-11T17:13:00.959Z","guessed":false,"streak":1,"srsNextAt":null,"srsLevel":0},"ch1mcq1":{"attempts":1,"correct":1,"lastResult":"correct","lastAt":"2026-06-11T17:13:27.489Z","guessed":false,"streak":1,"srsNextAt":null,"srsLevel":0},"ch1mcq2":{"attempts":1,"correct":1,"lastResult":"correct","lastAt":"2026-06-11T17:13:47.977Z","guessed":false,"streak":1,"srsNextAt":null,"srsLevel":0},"cn-c1-q01":{"attempts":1,"correct":1,"lastResult":"correct","lastAt":"2026-06-11T17:15:15.622Z","guessed":false,"streak":1,"srsNextAt":null,"srsLevel":0},"cn-c1-q02":{"attempts":1,"correct":1,"lastResult":"correct","lastAt":"2026-06-11T17:15:35.655Z","guessed":false,"streak":1,"srsNextAt":null,"srsLevel":0},"cn-c1-q03":{"attempts":1,"correct":1,"lastResult":"correct","lastAt":"2026-06-11T17:15:49.622Z","guessed":false,"streak":1,"srsNextAt":null,"srsLevel":0},"cn-c1-q04":{"attempts":1,"correct":1,"lastResult":"correct","lastAt":"2026-06-11T17:16:05.288Z","guessed":false,"streak":1,"srsNextAt":null,"srsLevel":0},"cn-c1-q05":{"attempts":1,"correct":1,"lastResult":"correct","lastAt":"2026-06-11T17:16:59.650Z","guessed":false,"streak":1,"srsNextAt":null,"srsLevel":0},"cn-c1-q07":{"attempts":1,"correct":1,"lastResult":"correct","lastAt":"2026-06-11T17:19:21.687Z","guessed":false,"streak":1,"srsNextAt":null,"srsLevel":0},"cn-c1-q08":{"attempts":1,"correct":1,"lastResult":"correct","lastAt":"2026-06-11T17:19:37.920Z","guessed":false,"streak":1,"srsNextAt":null,"srsLevel":0},"cn-c1-q09":{"attempts":1,"correct":1,"lastResult":"correct","lastAt":"2026-06-11T17:20:18.785Z","guessed":false,"streak":1,"srsNextAt":null,"srsLevel":0},"cn-c1-q10":{"attempts":1,"correct":1,"lastResult":"correct","lastAt":"2026-06-11T17:20:50.523Z","guessed":false,"streak":1,"srsNextAt":null,"srsLevel":0},"cn-c1-q11":{"attempts":1,"correct":0,"lastResult":"wrong","lastAt":"2026-06-11T17:21:20.551Z","guessed":false,"streak":0,"srsNextAt":"2026-06-12T17:21:20.551Z","srsLevel":0},"cn-c1-q12":{"attempts":1,"correct":0,"lastResult":"wrong","lastAt":"2026-06-11T17:26:26.329Z","guessed":false,"streak":0,"srsNextAt":"2026-06-12T17:26:26.329Z","srsLevel":0},"phy-c1-d01":{"attempts":2,"correct":2,"lastResult":"correct","lastAt":"2026-06-12T03:32:08.433Z","guessed":false,"streak":2,"srsNextAt":null,"srsLevel":0},"phy-c1-d02":{"attempts":2,"correct":2,"lastResult":"correct","lastAt":"2026-06-12T03:32:32.594Z","guessed":false,"streak":2,"srsNextAt":null,"srsLevel":0},"phy-c1-d03":{"attempts":1,"correct":1,"lastResult":"correct","lastAt":"2026-06-12T03:32:53.678Z","guessed":false,"streak":1,"srsNextAt":null,"srsLevel":0},"phy-c1-d04":{"attempts":1,"correct":1,"lastResult":"correct","lastAt":"2026-06-12T03:33:24.611Z","guessed":false,"streak":1,"srsNextAt":null,"srsLevel":0},"phy-c2-m30":{"attempts":1,"correct":1,"lastResult":"correct","lastAt":"2026-06-12T11:27:19.134Z","guessed":false,"streak":1,"srsNextAt":null,"srsLevel":0},"c4ar1":{"attempts":1,"correct":1,"lastResult":"correct","lastAt":"2026-06-12T11:31:59.885Z","guessed":false,"streak":1,"srsNextAt":null,"srsLevel":0},"phy-c4-m25":{"attempts":1,"correct":1,"lastResult":"correct","lastAt":"2026-06-12T11:34:49.547Z","guessed":false,"streak":1,"srsNextAt":null,"srsLevel":0},"geo-ch1-mcq020":{"attempts":1,"correct":1,"lastResult":"correct","lastAt":"2026-06-12T15:39:40.202Z","guessed":false,"streak":1,"srsNextAt":null,"srsLevel":0},"geo-ch1-mcq062":{"attempts":1,"correct":1,"lastResult":"correct","lastAt":"2026-06-12T15:39:40.204Z","guessed":false,"streak":1,"srsNextAt":null,"srsLevel":0},"geo-ch1-mcq052":{"attempts":1,"correct":0,"lastResult":"wrong","lastAt":"2026-06-12T15:39:40.204Z","guessed":false,"streak":0,"srsNextAt":"2026-06-13T15:39:40.204Z","srsLevel":0},"geo-ch1-mcq006":{"attempts":1,"correct":0,"lastResult":"wrong","lastAt":"2026-06-12T15:39:40.205Z","guessed":false,"streak":0,"srsNextAt":"2026-06-13T15:39:40.205Z","srsLevel":0},"geo-ch1-mcq061":{"attempts":1,"correct":1,"lastResult":"correct","lastAt":"2026-06-12T15:39:40.205Z","guessed":false,"streak":1,"srsNextAt":null,"srsLevel":0},"geo-ch1-mcq005":{"attempts":1,"correct":0,"lastResult":"wrong","lastAt":"2026-06-12T15:39:40.206Z","guessed":false,"streak":0,"srsNextAt":"2026-06-13T15:39:40.206Z","srsLevel":0},"geo-ch1-mcq060":{"attempts":1,"correct":1,"lastResult":"correct","lastAt":"2026-06-12T15:39:40.206Z","guessed":false,"streak":1,"srsNextAt":null,"srsLevel":0},"geo-ch1-tf03":{"attempts":1,"correct":1,"lastResult":"correct","lastAt":"2026-06-12T15:39:40.206Z","guessed":false,"streak":1,"srsNextAt":null,"srsLevel":0},"geo-ch1-mcq010":{"attempts":1,"correct":1,"lastResult":"correct","lastAt":"2026-06-12T15:39:40.207Z","guessed":false,"streak":1,"srsNextAt":null,"srsLevel":0},"geo-ch1-mcq058":{"attempts":1,"correct":1,"lastResult":"correct","lastAt":"2026-06-12T15:39:40.207Z","guessed":false,"streak":1,"srsNextAt":null,"srsLevel":0},"geo-ch1-mcq009":{"attempts":1,"correct":0,"lastResult":"wrong","lastAt":"2026-06-12T15:39:40.208Z","guessed":false,"streak":0,"srsNextAt":"2026-06-13T15:39:40.208Z","srsLevel":0},"geo-ch1-mcq025":{"attempts":1,"correct":1,"lastResult":"correct","lastAt":"2026-06-12T15:39:40.208Z","guessed":false,"streak":1,"srsNextAt":null,"srsLevel":0},"geo-ch1-mcq050":{"attempts":1,"correct":1,"lastResult":"correct","lastAt":"2026-06-12T15:39:40.208Z","guessed":false,"streak":1,"srsNextAt":null,"srsLevel":0},"geo-ch1-mcq038":{"attempts":1,"correct":0,"lastResult":"wrong","lastAt":"2026-06-12T15:39:40.209Z","guessed":false,"streak":0,"srsNextAt":"2026-06-13T15:39:40.209Z","srsLevel":0},"geo-ch1-mcq051":{"attempts":1,"correct":0,"lastResult":"wrong","lastAt":"2026-06-12T15:39:40.209Z","guessed":false,"streak":0,"srsNextAt":"2026-06-13T15:39:40.209Z","srsLevel":0},"geo-ch1-mcq035":{"attempts":1,"correct":0,"lastResult":"wrong","lastAt":"2026-06-12T15:39:40.209Z","guessed":false,"streak":0,"srsNextAt":"2026-06-13T15:39:40.209Z","srsLevel":0},"geo-ch1-tf06":{"attempts":1,"correct":1,"lastResult":"correct","lastAt":"2026-06-12T15:39:40.210Z","guessed":false,"streak":1,"srsNextAt":null,"srsLevel":0},"geo-ch1-mcq023":{"attempts":1,"correct":1,"lastResult":"correct","lastAt":"2026-06-12T15:39:40.210Z","guessed":false,"streak":1,"srsNextAt":null,"srsLevel":0},"geo-ch1-mcq004":{"attempts":1,"correct":0,"lastResult":"wrong","lastAt":"2026-06-12T15:39:40.210Z","guessed":false,"streak":0,"srsNextAt":"2026-06-13T15:39:40.210Z","srsLevel":0},"geo-ch1-tf01":{"attempts":1,"correct":1,"lastResult":"correct","lastAt":"2026-06-12T15:39:40.211Z","guessed":false,"streak":1,"srsNextAt":null,"srsLevel":0},"bqp-ch01-q01":{"attempts":1,"correct":0,"lastResult":"seen","lastAt":"2026-06-12T23:40:41.665Z","guessed":false,"streak":0,"srsNextAt":null,"srsLevel":0},"bqp-ch01-q02":{"attempts":1,"correct":0,"lastResult":"seen","lastAt":"2026-06-12T23:41:21.723Z","guessed":false,"streak":0,"srsNextAt":null,"srsLevel":0},"bqp-ch01-q26":{"attempts":1,"correct":0,"lastResult":"seen","lastAt":"2026-06-13T00:08:55.589Z","guessed":false,"streak":0,"srsNextAt":null,"srsLevel":0},"bqp-ch01-q27":{"attempts":1,"correct":0,"lastResult":"seen","lastAt":"2026-06-13T00:09:18.355Z","guessed":false,"streak":0,"srsNextAt":null,"srsLevel":0},"bqp-ch01-q29":{"attempts":1,"correct":0,"lastResult":"seen","lastAt":"2026-06-13T00:10:07.665Z","guessed":false,"streak":0,"srsNextAt":null,"srsLevel":0},"bqp-ch01-q30":{"attempts":1,"correct":0,"lastResult":"seen","lastAt":"2026-06-13T00:10:18.538Z","guessed":false,"streak":0,"srsNextAt":null,"srsLevel":0},"bqp-ch01-q34":{"attempts":1,"correct":0,"lastResult":"seen","lastAt":"2026-06-13T00:10:55.771Z","guessed":false,"streak":0,"srsNextAt":null,"srsLevel":0},"bqp-ch01-q35":{"attempts":1,"correct":0,"lastResult":"seen","lastAt":"2026-06-13T00:11:28.870Z","guessed":false,"streak":0,"srsNextAt":null,"srsLevel":0},"b1x-sa1":{"attempts":1,"correct":0,"lastResult":"seen","lastAt":"2026-06-13T00:11:36.137Z","guessed":false,"streak":0,"srsNextAt":null,"srsLevel":0},"b1x-sa2":{"attempts":1,"correct":0,"lastResult":"seen","lastAt":"2026-06-13T00:11:44.130Z","guessed":false,"streak":0,"srsNextAt":null,"srsLevel":0},"bqp-ch03-q02":{"attempts":1,"correct":0,"lastResult":"seen","lastAt":"2026-06-13T00:12:18.146Z","guessed":false,"streak":0,"srsNextAt":null,"srsLevel":0},"b3kb-sa10":{"attempts":1,"correct":0,"lastResult":"seen","lastAt":"2026-06-13T00:13:27.486Z","guessed":false,"streak":0,"srsNextAt":null,"srsLevel":0},"b3kb-sa1":{"attempts":1,"correct":0,"lastResult":"seen","lastAt":"2026-06-13T00:13:37.055Z","guessed":false,"streak":0,"srsNextAt":null,"srsLevel":0},"b3kb-sa3":{"attempts":1,"correct":0,"lastResult":"seen","lastAt":"2026-06-13T00:13:43.854Z","guessed":false,"streak":0,"srsNextAt":null,"srsLevel":0},"b3kb-sa4":{"attempts":1,"correct":0,"lastResult":"seen","lastAt":"2026-06-13T00:13:46.886Z","guessed":false,"streak":0,"srsNextAt":null,"srsLevel":0},"b3kb-sa5":{"attempts":1,"correct":0,"lastResult":"seen","lastAt":"2026-06-13T00:13:50.987Z","guessed":false,"streak":0,"srsNextAt":null,"srsLevel":0},"b3kb-sa6":{"attempts":1,"correct":0,"lastResult":"seen","lastAt":"2026-06-13T00:13:59.019Z","guessed":false,"streak":0,"srsNextAt":null,"srsLevel":0},"phy-c1-s03":{"attempts":1,"correct":0,"lastResult":"seen","lastAt":"2026-06-13T00:47:49.981Z","guessed":false,"streak":0,"srsNextAt":null,"srsLevel":0},"phy-c1-s01":{"attempts":1,"correct":0,"lastResult":"seen","lastAt":"2026-06-13T00:51:07.804Z","guessed":false,"streak":0,"srsNextAt":null,"srsLevel":0},"pqb-ch1-matter-11":{"attempts":1,"correct":0,"lastResult":"seen","lastAt":"2026-06-13T00:51:45.890Z","guessed":false,"streak":0,"srsNextAt":null,"srsLevel":0},"pqb-ch1-matter-12":{"attempts":1,"correct":0,"lastResult":"seen","lastAt":"2026-06-13T00:54:23.671Z","guessed":false,"streak":0,"srsNextAt":null,"srsLevel":0},"pqb-ch1-matter-13":{"attempts":1,"correct":0,"lastResult":"seen","lastAt":"2026-06-13T00:58:42.970Z","guessed":false,"streak":0,"srsNextAt":null,"srsLevel":0},"pqb-ch1-matter-18":{"attempts":1,"correct":0,"lastResult":"seen","lastAt":"2026-06-13T00:59:23.954Z","guessed":false,"streak":0,"srsNextAt":null,"srsLevel":0},"pqb-ch1-matter-15":{"attempts":1,"correct":0,"lastResult":"seen","lastAt":"2026-06-13T00:59:52.255Z","guessed":false,"streak":0,"srsNextAt":null,"srsLevel":0},"pqb-ch1-matter-16":{"attempts":1,"correct":0,"lastResult":"seen","lastAt":"2026-06-13T01:02:02.602Z","guessed":false,"streak":0,"srsNextAt":null,"srsLevel":0},"pqb-ch1-matter-17":{"attempts":1,"correct":0,"lastResult":"seen","lastAt":"2026-06-13T01:02:09.920Z","guessed":false,"streak":0,"srsNextAt":null,"srsLevel":0},"pqb-ch1-matter-19":{"attempts":1,"correct":0,"lastResult":"seen","lastAt":"2026-06-13T01:03:02.286Z","guessed":false,"streak":0,"srsNextAt":null,"srsLevel":0},"pqb-ch1-matter-1":{"attempts":1,"correct":0,"lastResult":"seen","lastAt":"2026-06-13T01:05:45.685Z","guessed":false,"streak":0,"srsNextAt":null,"srsLevel":0}},"bookmarks":["b1ocr-cfq3","phy-s1-q127"],"activity":{"2026-06-10":{"mcqs":37},"2026-06-11":{"mcqs":22},"2026-06-12":{"mcqs":27}},"questionRatings":{"ch1ar1":{"votes":{"dev-mq8ihaj2nbchxg":5}},"ch1mcq1":{"votes":{"dev-mq8ihaj2nbchxg":5}},"ch1mcq2":{"votes":{"dev-mq8ihaj2nbchxg":5}}}}